[{"text": "Saturday Morning Political Cartoon Thread", "external_id": null, "error": false, "extractions": [{"tag_name": "KEYWORD", "parsed_value": "morning political cartoon", "count": 1, "relevance": "0.968", "positions_in_text": [9]}, {"tag_name": "KEYWORD", "parsed_value": "political cartoon thread", "count": 1, "relevance": "0.968", "positions_in_text": [17]}, {"tag_name": "KEYWORD", "parsed_value": "saturday morning political", "count": 1, "relevance": "0.968", "positions_in_text": [0]}]}, {"text": "Marijuana is only legal in 11 states but a House vote coming next month could expand legalization to the entire US", "external_id": null, "error": false, "extractions": [{"tag_name": "KEYWORD", "parsed_value": "entire us", "count": 1, "relevance": "0.952", "positions_in_text": [105]}, {"tag_name": "KEYWORD", "parsed_value": "next month", "count": 1, "relevance": "0.952", "positions_in_text": [61]}, {"tag_name": "KEYWORD", "parsed_value": "house vote", "count": 1, "relevance": "0.952", "positions_in_text": [43]}, {"tag_name": "KEYWORD", "parsed_value": "legalization", "count": 1, "relevance": "0.476", "positions_in_text": [85]}, {"tag_name": "KEYWORD", "parsed_value": "state", "count": 1, "relevance": "0.476", "positions_in_text": [30]}, {"tag_name": "KEYWORD", "parsed_value": "marijuana", "count": 1, "relevance": "0.476", "positions_in_text": [0]}]}, {"text": "Schiff and Pelosi call cancellation of election security briefings a \"shocking abdication\" of \"responsibility\"", "external_id": null, "error": false, "extractions": [{"tag_name": "KEYWORD", "parsed_value": "cancellation of election", "count": 1, "relevance": "0.968", "positions_in_text": [23]}, {"tag_name": "KEYWORD", "parsed_value": "election security briefing", "count": 1, "relevance": "0.968", "positions_in_text": [39]}, {"tag_name": "KEYWORD", "parsed_value": "shocking abdication", "count": 1, "relevance": "0.645", "positions_in_text": [70]}, {"tag_name": "KEYWORD", "parsed_value": "schiff", "count": 1, "relevance": "0.323", "positions_in_text": [0]}, {"tag_name": "KEYWORD", "parsed_value": "responsibility", "count": 1, "relevance": "0.323", "positions_in_text": [95]}, {"tag_name": "KEYWORD", "parsed_value": "pelosi", "count": 1, "relevance": "0.323", "positions_in_text": [11]}]}, {"text": "Speaker Pelosi and Chairman Schiff Statement on Cancellation of Election Security Briefings by Office of the Director of National Intelligence", "external_id": null, "error": false, "extractions": [{"tag_name": "KEYWORD", "parsed_value": "chairman schiff statement", "count": 1, "relevance": "0.968", "positions_in_text": [19]}, {"tag_name": "KEYWORD", "parsed_value": "cancellation of election", "count": 1, "relevance": "0.968", "positions_in_text": [48]}, {"tag_name": "KEYWORD", "parsed_value": "director of national", "count": 1, "relevance": "0.968", "positions_in_text": [109]}, {"tag_name": "KEYWORD", "parsed_value": "election security briefing", "count": 1, "relevance": "0.968", "positions_in_text": [64]}, {"tag_name": "KEYWORD", "parsed_value": "speaker pelosi", "count": 1, "relevance": "0.645", "positions_in_text": [0]}, {"tag_name": "KEYWORD", "parsed_value": "national intelligence", "count": 1, "relevance": "0.645", "positions_in_text": [121]}, {"tag_name": "KEYWORD", "parsed_value": "office", "count": 1, "relevance": "0.323", "positions_in_text": [95]}]}, {"text": "50,000 people in Iowa will need to request another absentee ballot after a judge sided with the Trump administration and invalidated their requests", "external_id": null, "error": false, "extractions": [{"tag_name": "KEYWORD", "parsed_value": "absentee ballot", "count": 1, "relevance": "0.952", "positions_in_text": [51]}, {"tag_name": "KEYWORD", "parsed_value": "trump administration", "count": 1, "relevance": "0.952", "positions_in_text": [96]}, {"tag_name": "KEYWORD", "parsed_value": "iowa", "count": 1, "relevance": "0.476", "positions_in_text": [17]}, {"tag_name": "KEYWORD", "parsed_value": "people", "count": 1, "relevance": "0.476", "positions_in_text": [7]}, {"tag_name": "KEYWORD", "parsed_value": "request", "count": 1, "relevance": "0.476", "positions_in_text": [139]}, {"tag_name": "KEYWORD", "parsed_value": "judge", "count": 1, "relevance": "0.476", "positions_in_text": [75]}]}, {"text": "Trump\u2019s Message Isn\u2019t Confused. He\u2019s Promising A Dictatorship. - The RNC doesn\u2019t need a platform because it will be whatever the president wants.", "external_id": null, "error": false, "extractions": [{"tag_name": "KEYWORD", "parsed_value": "platform", "count": 1, "relevance": "0.909", "positions_in_text": [88]}, {"tag_name": "KEYWORD", "parsed_value": "trump", "count": 1, "relevance": "0.909", "positions_in_text": [0]}, {"tag_name": "KEYWORD", "parsed_value": "dictatorship", "count": 1, "relevance": "0.909", "positions_in_text": [49]}, {"tag_name": "KEYWORD", "parsed_value": "promising", "count": 1, "relevance": "0.909", "positions_in_text": [37]}, {"tag_name": "KEYWORD", "parsed_value": "rnc", "count": 1, "relevance": "0.909", "positions_in_text": [69]}, {"tag_name": "KEYWORD", "parsed_value": "president", "count": 1, "relevance": "0.909", "positions_in_text": [129]}, {"tag_name": "KEYWORD", "parsed_value": "message", "count": 1, "relevance": "0.909", "positions_in_text": [8]}]}, {"text": "Who Really Cares About the Hatch Act? Lots of People \u2014 and You Should, Too", "external_id": null, "error": false, "extractions": [{"tag_name": "KEYWORD", "parsed_value": "lot of people", "count": 1, "relevance": "0.968", "positions_in_text": [38]}, {"tag_name": "KEYWORD", "parsed_value": "hatch act", "count": 1, "relevance": "0.645", "positions_in_text": [27]}]}, {"text": "Michael Moore warns that Donald Trump is on course to repeat 2016 win | Film-maker says enthusiasm for president in swing states is \u2018off the charts\u2019 and urges everyone to commit to getting 100 people to vote", "external_id": null, "error": false, "extractions": [{"tag_name": "KEYWORD", "parsed_value": "donald trump", "count": 1, "relevance": "0.952", "positions_in_text": [25]}, {"tag_name": "KEYWORD", "parsed_value": "swing state", "count": 1, "relevance": "0.952", "positions_in_text": [116]}, {"tag_name": "KEYWORD", "parsed_value": "michael moore", "count": 1, "relevance": "0.952", "positions_in_text": [0]}, {"tag_name": "KEYWORD", "parsed_value": "everyone", "count": 1, "relevance": "0.476", "positions_in_text": [159]}, {"tag_name": "KEYWORD", "parsed_value": "people", "count": 1, "relevance": "0.476", "positions_in_text": [193]}, {"tag_name": "KEYWORD", "parsed_value": "course", "count": 1, "relevance": "0.476", "positions_in_text": [44]}, {"tag_name": "KEYWORD", "parsed_value": "enthusiasm", "count": 1, "relevance": "0.476", "positions_in_text": [88]}, {"tag_name": "KEYWORD", "parsed_value": "president", "count": 1, "relevance": "0.476", "positions_in_text": [103]}, {"tag_name": "KEYWORD", "parsed_value": "maker", "count": 1, "relevance": "0.476", "positions_in_text": [77]}, {"tag_name": "KEYWORD", "parsed_value": "film", "count": 1, "relevance": "0.476", "positions_in_text": [72]}]}, {"text": "Leonard Cohen\u2019s Estate May Sue Donald Trump for Unauthorized Use of \u201cHallelujah\u201d", "external_id": null, "error": false, "extractions": [{"tag_name": "KEYWORD", "parsed_value": "sue donald trump", "count": 1, "relevance": "0.968", "positions_in_text": [27]}, {"tag_name": "KEYWORD", "parsed_value": "leonard cohen", "count": 1, "relevance": "0.645", "positions_in_text": [0]}, {"tag_name": "KEYWORD", "parsed_value": "unauthorized use", "count": 1, "relevance": "0.645", "positions_in_text": [48]}, {"tag_name": "KEYWORD", "parsed_value": "estate", "count": 1, "relevance": "0.323", "positions_in_text": [16]}, {"tag_name": "KEYWORD", "parsed_value": "hallelujah", "count": 1, "relevance": "0.323", "positions_in_text": [69]}]}, {"text": "Noam Chomsky: 'There's never been a moment in human history' like this one", "external_id": null, "error": false, "extractions": [{"tag_name": "KEYWORD", "parsed_value": "human history", "count": 1, "relevance": "0.952", "positions_in_text": [46]}, {"tag_name": "KEYWORD", "parsed_value": "noam chomsky", "count": 1, "relevance": "0.952", "positions_in_text": [0]}, {"tag_name": "KEYWORD", "parsed_value": "moment", "count": 1, "relevance": "0.476", "positions_in_text": [36]}]}, {"text": "Top intelligence office informs congressional committees it'll no longer brief on election security", "external_id": null, "error": false, "extractions": [{"tag_name": "KEYWORD", "parsed_value": "top intelligence office", "count": 1, "relevance": "0.968", "positions_in_text": [0]}, {"tag_name": "KEYWORD", "parsed_value": "congressional committee", "count": 1, "relevance": "0.645", "positions_in_text": [32]}, {"tag_name": "KEYWORD", "parsed_value": "election security", "count": 1, "relevance": "0.645", "positions_in_text": [82]}]}, {"text": "The Republican National Committee used stock footage from a 2019 protest in Spain to show rioting in 'Biden's America'", "external_id": null, "error": false, "extractions": [{"tag_name": "KEYWORD", "parsed_value": "republican national committee", "count": 1, "relevance": "0.968", "positions_in_text": [4]}, {"tag_name": "KEYWORD", "parsed_value": "stock footage", "count": 1, "relevance": "0.645", "positions_in_text": [39]}, {"tag_name": "KEYWORD", "parsed_value": "rioting", "count": 1, "relevance": "0.323", "positions_in_text": [90]}, {"tag_name": "KEYWORD", "parsed_value": "biden", "count": 1, "relevance": "0.323", "positions_in_text": [102]}, {"tag_name": "KEYWORD", "parsed_value": "protest", "count": 1, "relevance": "0.323", "positions_in_text": [65]}, {"tag_name": "KEYWORD", "parsed_value": "america", "count": 1, "relevance": "0.323", "positions_in_text": [110]}, {"tag_name": "KEYWORD", "parsed_value": "spain", "count": 1, "relevance": "0.323", "positions_in_text": [76]}]}, {"text": "Data show Trump didn't 'build' a great economy. He inherited it. The average quarterly economic growth under Trump, 2.5 percent, was almost exactly what it was under Obama in the second term, 2.4 percent.", "external_id": null, "error": false, "extractions": [{"tag_name": "KEYWORD", "parsed_value": "quarterly economic growth", "count": 1, "relevance": "0.968", "positions_in_text": [77]}, {"tag_name": "KEYWORD", "parsed_value": "trump", "count": 2, "relevance": "0.645", "positions_in_text": [10, 109]}, {"tag_name": "KEYWORD", "parsed_value": "great economy", "count": 1, "relevance": "0.645", "positions_in_text": [33]}, {"tag_name": "KEYWORD", "parsed_value": "percent", "count": 2, "relevance": "0.645", "positions_in_text": [120, 196]}, {"tag_name": "KEYWORD", "parsed_value": "second terms", "count": 1, "relevance": "0.645", "positions_in_text": [179]}, {"tag_name": "KEYWORD", "parsed_value": "data", "count": 1, "relevance": "0.323", "positions_in_text": [0]}, {"tag_name": "KEYWORD", "parsed_value": "obama", "count": 1, "relevance": "0.323", "positions_in_text": [166]}]}, {"text": "Federal court defies Trump & grants U.S. citizenship to gay dads\u2019 two-year-old daughter \u2014 The State Department's handling of the case was needlessly cruel and furthered no compelling government interest, according to Immigration Equality.", "external_id": null, "error": false, "extractions": [{"tag_name": "KEYWORD", "parsed_value": "grant u.s. citizenship", "count": 1, "relevance": "0.968", "positions_in_text": [29]}, {"tag_name": "KEYWORD", "parsed_value": "trump & grant", "count": 1, "relevance": "0.968", "positions_in_text": [21]}, {"tag_name": "KEYWORD", "parsed_value": "compelling government interest", "count": 1, "relevance": "0.968", "positions_in_text": [172]}, {"tag_name": "KEYWORD", "parsed_value": "state department", "count": 1, "relevance": "0.645", "positions_in_text": [94]}, {"tag_name": "KEYWORD", "parsed_value": "federal court", "count": 1, "relevance": "0.645", "positions_in_text": [0]}, {"tag_name": "KEYWORD", "parsed_value": "old daughter", "count": 1, "relevance": "0.645", "positions_in_text": [75]}, {"tag_name": "KEYWORD", "parsed_value": "immigration equality", "count": 1, "relevance": "0.645", "positions_in_text": [217]}, {"tag_name": "KEYWORD", "parsed_value": "year", "count": 1, "relevance": "0.323", "positions_in_text": [70]}, {"tag_name": "KEYWORD", "parsed_value": "case", "count": 1, "relevance": "0.323", "positions_in_text": [129]}, {"tag_name": "KEYWORD", "parsed_value": "handling", "count": 1, "relevance": "0.323", "positions_in_text": [113]}]}, {"text": "Staring down Trump, Kamala Harris says she stands with protesters on racial equality", "external_id": null, "error": false, "extractions": [{"tag_name": "KEYWORD", "parsed_value": "kamala harris", "count": 1, "relevance": "0.952", "positions_in_text": [20]}, {"tag_name": "KEYWORD", "parsed_value": "racial equality", "count": 1, "relevance": "0.952", "positions_in_text": [69]}, {"tag_name": "KEYWORD", "parsed_value": "protesters", "count": 1, "relevance": "0.476", "positions_in_text": [55]}, {"tag_name": "KEYWORD", "parsed_value": "trump", "count": 1, "relevance": "0.476", "positions_in_text": [13]}]}, {"text": "Trump blames media after DNC tops RNC in TV ratings. Biden's speech also drew more viewers than Trump's speech a week later.", "external_id": null, "error": false, "extractions": [{"tag_name": "KEYWORD", "parsed_value": "trump", "count": 2, "relevance": "0.952", "positions_in_text": [0, 96]}, {"tag_name": "KEYWORD", "parsed_value": "speech", "count": 2, "relevance": "0.952", "positions_in_text": [61, 104]}, {"tag_name": "KEYWORD", "parsed_value": "tv rating", "count": 1, "relevance": "0.952", "positions_in_text": [41]}, {"tag_name": "KEYWORD", "parsed_value": "week", "count": 1, "relevance": "0.476", "positions_in_text": [113]}, {"tag_name": "KEYWORD", "parsed_value": "media", "count": 1, "relevance": "0.476", "positions_in_text": [13]}, {"tag_name": "KEYWORD", "parsed_value": "dnc", "count": 1, "relevance": "0.476", "positions_in_text": [25]}, {"tag_name": "KEYWORD", "parsed_value": "rnc", "count": 1, "relevance": "0.476", "positions_in_text": [34]}, {"tag_name": "KEYWORD", "parsed_value": "biden", "count": 1, "relevance": "0.476", "positions_in_text": [53]}, {"tag_name": "KEYWORD", "parsed_value": "viewer", "count": 1, "relevance": "0.476", "positions_in_text": [83]}]}, {"text": "Professional Athletes Are Showing America Just How Powerful Labor Really Is - By striking, the players in the NBA, MLB, and beyond have brought their bosses to the table and launched a national conversation.", "external_id": null, "error": false, "extractions": [{"tag_name": "KEYWORD", "parsed_value": "powerful labor", "count": 1, "relevance": "0.952", "positions_in_text": [51]}, {"tag_name": "KEYWORD", "parsed_value": "professional athletes", "count": 1, "relevance": "0.952", "positions_in_text": [0]}, {"tag_name": "KEYWORD", "parsed_value": "national conversation", "count": 1, "relevance": "0.952", "positions_in_text": [185]}, {"tag_name": "KEYWORD", "parsed_value": "mlb", "count": 1, "relevance": "0.476", "positions_in_text": [115]}, {"tag_name": "KEYWORD", "parsed_value": "america", "count": 1, "relevance": "0.476", "positions_in_text": [34]}, {"tag_name": "KEYWORD", "parsed_value": "striking", "count": 1, "relevance": "0.476", "positions_in_text": [81]}, {"tag_name": "KEYWORD", "parsed_value": "bosses", "count": 1, "relevance": "0.476", "positions_in_text": [150]}, {"tag_name": "KEYWORD", "parsed_value": "player", "count": 1, "relevance": "0.476", "positions_in_text": [95]}, {"tag_name": "KEYWORD", "parsed_value": "table", "count": 1, "relevance": "0.476", "positions_in_text": [164]}, {"tag_name": "KEYWORD", "parsed_value": "nba", "count": 1, "relevance": "0.476", "positions_in_text": [110]}]}, {"text": "Trump is the president of the loud minority, not silent majority", "external_id": null, "error": false, "extractions": [{"tag_name": "KEYWORD", "parsed_value": "loud minority", "count": 1, "relevance": "0.952", "positions_in_text": [30]}, {"tag_name": "KEYWORD", "parsed_value": "silent majority", "count": 1, "relevance": "0.952", "positions_in_text": [49]}, {"tag_name": "KEYWORD", "parsed_value": "president", "count": 1, "relevance": "0.476", "positions_in_text": [13]}, {"tag_name": "KEYWORD", "parsed_value": "trump", "count": 1, "relevance": "0.476", "positions_in_text": [0]}]}, {"text": "Trump administration ends election security briefings", "external_id": null, "error": false, "extractions": [{"tag_name": "KEYWORD", "parsed_value": "election security briefing", "count": 1, "relevance": "0.968", "positions_in_text": [26]}, {"tag_name": "KEYWORD", "parsed_value": "trump administration", "count": 1, "relevance": "0.645", "positions_in_text": [0]}]}, {"text": "Trump Is Laying the Groundwork to Reject the Results of the Election", "external_id": null, "error": false, "extractions": [{"tag_name": "KEYWORD", "parsed_value": "groundwork", "count": 1, "relevance": "0.909", "positions_in_text": [20]}, {"tag_name": "KEYWORD", "parsed_value": "results", "count": 1, "relevance": "0.909", "positions_in_text": [45]}, {"tag_name": "KEYWORD", "parsed_value": "election", "count": 1, "relevance": "0.909", "positions_in_text": [60]}, {"tag_name": "KEYWORD", "parsed_value": "trump", "count": 1, "relevance": "0.909", "positions_in_text": [0]}]}, {"text": "Kanye West Wisconsin Ballot Lawsuit Linked To Firm Of Former RNC Chief Counsel", "external_id": null, "error": false, "extractions": [{"tag_name": "KEYWORD", "parsed_value": "west wisconsin ballot", "count": 1, "relevance": "0.968", "positions_in_text": [6]}, {"tag_name": "KEYWORD", "parsed_value": "rnc chief counsel", "count": 1, "relevance": "0.968", "positions_in_text": [61]}, {"tag_name": "KEYWORD", "parsed_value": "former rnc chief", "count": 1, "relevance": "0.968", "positions_in_text": [54]}, {"tag_name": "KEYWORD", "parsed_value": "kanye west wisconsin", "count": 1, "relevance": "0.968", "positions_in_text": [0]}, {"tag_name": "KEYWORD", "parsed_value": "wisconsin ballot lawsuit", "count": 1, "relevance": "0.968", "positions_in_text": [11]}, {"tag_name": "KEYWORD", "parsed_value": "firm", "count": 1, "relevance": "0.323", "positions_in_text": [46]}]}, {"text": "Trump's dire warnings are not about Biden's America. They're about his America", "external_id": null, "error": false, "extractions": [{"tag_name": "KEYWORD", "parsed_value": "dire warning", "count": 1, "relevance": "0.952", "positions_in_text": [8]}, {"tag_name": "KEYWORD", "parsed_value": "america", "count": 2, "relevance": "0.952", "positions_in_text": [44, 71]}, {"tag_name": "KEYWORD", "parsed_value": "biden", "count": 1, "relevance": "0.476", "positions_in_text": [36]}, {"tag_name": "KEYWORD", "parsed_value": "trump", "count": 1, "relevance": "0.476", "positions_in_text": [0]}]}, {"text": "Suburban Voters Say Trump Never Addressed COVID-19, Racial Unrest at RNC: 'Simply Ignored It'", "external_id": null, "error": false, "extractions": [{"tag_name": "KEYWORD", "parsed_value": "racial unrest", "count": 1, "relevance": "0.952", "positions_in_text": [52]}, {"tag_name": "KEYWORD", "parsed_value": "suburban voters", "count": 1, "relevance": "0.952", "positions_in_text": [0]}, {"tag_name": "KEYWORD", "parsed_value": "addressed covid-19", "count": 1, "relevance": "0.952", "positions_in_text": [32]}, {"tag_name": "KEYWORD", "parsed_value": "trump", "count": 1, "relevance": "0.476", "positions_in_text": [20]}, {"tag_name": "KEYWORD", "parsed_value": "rnc", "count": 1, "relevance": "0.476", "positions_in_text": [69]}]}, {"text": "Secret service agents are battling coronavirus cases as Trump campaign continues to host in-person gatherings: report", "external_id": null, "error": false, "extractions": [{"tag_name": "KEYWORD", "parsed_value": "secret services agent", "count": 1, "relevance": "0.968", "positions_in_text": [0]}, {"tag_name": "KEYWORD", "parsed_value": "trump campaign", "count": 1, "relevance": "0.645", "positions_in_text": [56]}, {"tag_name": "KEYWORD", "parsed_value": "coronavirus case", "count": 1, "relevance": "0.645", "positions_in_text": [35]}, {"tag_name": "KEYWORD", "parsed_value": "person gathering", "count": 1, "relevance": "0.645", "positions_in_text": [92]}]}, {"text": "Census, like the Postal Service, has been politicized in an election year", "external_id": null, "error": false, "extractions": [{"tag_name": "KEYWORD", "parsed_value": "postal services", "count": 1, "relevance": "0.952", "positions_in_text": [17]}, {"tag_name": "KEYWORD", "parsed_value": "election year", "count": 1, "relevance": "0.952", "positions_in_text": [60]}, {"tag_name": "KEYWORD", "parsed_value": "census", "count": 1, "relevance": "0.476", "positions_in_text": [0]}]}, {"text": "Mary Trump calls family speeches at RNC 'disturbing to watch'", "external_id": null, "error": false, "extractions": [{"tag_name": "KEYWORD", "parsed_value": "mary trump", "count": 1, "relevance": "0.952", "positions_in_text": [0]}, {"tag_name": "KEYWORD", "parsed_value": "family speech", "count": 1, "relevance": "0.952", "positions_in_text": [17]}, {"tag_name": "KEYWORD", "parsed_value": "rnc", "count": 1, "relevance": "0.476", "positions_in_text": [36]}]}, {"text": "Penn Professor Renews Call To Investigate Trump Admission To Ivy League School", "external_id": null, "error": false, "extractions": [{"tag_name": "KEYWORD", "parsed_value": "professor renews call", "count": 1, "relevance": "0.968", "positions_in_text": [5]}, {"tag_name": "KEYWORD", "parsed_value": "ivy league school", "count": 1, "relevance": "0.968", "positions_in_text": [61]}, {"tag_name": "KEYWORD", "parsed_value": "investigate trump admission", "count": 1, "relevance": "0.968", "positions_in_text": [30]}, {"tag_name": "KEYWORD", "parsed_value": "penn professor renews", "count": 1, "relevance": "0.968", "positions_in_text": [0]}]}, {"text": "D.C. drowns out Trump and the RNC \u2014 While Trump packed the White House with his supporters, D.C.\u2019s streets presented a thorough rejection of him, his policies, and all that he stands for.", "external_id": null, "error": false, "extractions": [{"tag_name": "KEYWORD", "parsed_value": "white house", "count": 1, "relevance": "0.952", "positions_in_text": [59]}, {"tag_name": "KEYWORD", "parsed_value": "d.c.", "count": 1, "relevance": "0.952", "positions_in_text": [0]}, {"tag_name": "KEYWORD", "parsed_value": "thorough rejection", "count": 1, "relevance": "0.952", "positions_in_text": [119]}, {"tag_name": "KEYWORD", "parsed_value": "trump", "count": 2, "relevance": "0.952", "positions_in_text": [16, 42]}, {"tag_name": "KEYWORD", "parsed_value": "rnc", "count": 1, "relevance": "0.476", "positions_in_text": [30]}, {"tag_name": "KEYWORD", "parsed_value": "street", "count": 1, "relevance": "0.476", "positions_in_text": [99]}, {"tag_name": "KEYWORD", "parsed_value": "policy", "count": 1, "relevance": "0.476", "positions_in_text": [150]}, {"tag_name": "KEYWORD", "parsed_value": "supporters", "count": 1, "relevance": "0.476", "positions_in_text": [80]}]}, {"text": "House committee begins work to hold Pompeo in contempt, accusing him of amplifying 'Putin's debunked conspiracy theories'", "external_id": null, "error": false, "extractions": [{"tag_name": "KEYWORD", "parsed_value": "debunked conspiracy theory", "count": 1, "relevance": "0.968", "positions_in_text": [92]}, {"tag_name": "KEYWORD", "parsed_value": "house committee", "count": 1, "relevance": "0.645", "positions_in_text": [0]}, {"tag_name": "KEYWORD", "parsed_value": "putin", "count": 1, "relevance": "0.323", "positions_in_text": [84]}, {"tag_name": "KEYWORD", "parsed_value": "pompeo", "count": 1, "relevance": "0.323", "positions_in_text": [36]}, {"tag_name": "KEYWORD", "parsed_value": "work", "count": 1, "relevance": "0.323", "positions_in_text": [23]}, {"tag_name": "KEYWORD", "parsed_value": "contempt", "count": 1, "relevance": "0.323", "positions_in_text": [46]}]}, {"text": "Trump\u2019s law and order campaign is \"falling flat\" in the Midwest: report", "external_id": null, "error": false, "extractions": [{"tag_name": "KEYWORD", "parsed_value": "order campaign", "count": 1, "relevance": "0.952", "positions_in_text": [16]}, {"tag_name": "KEYWORD", "parsed_value": "trump", "count": 1, "relevance": "0.476", "positions_in_text": [0]}, {"tag_name": "KEYWORD", "parsed_value": "report", "count": 1, "relevance": "0.476", "positions_in_text": [65]}, {"tag_name": "KEYWORD", "parsed_value": "law", "count": 1, "relevance": "0.476", "positions_in_text": [8]}, {"tag_name": "KEYWORD", "parsed_value": "midwest", "count": 1, "relevance": "0.476", "positions_in_text": [56]}]}, {"text": "Trump tells Hurricane Laura emergency responders to sell his autograph on eBay for $10k", "external_id": null, "error": false, "extractions": [{"tag_name": "KEYWORD", "parsed_value": "laura emergency responder", "count": 1, "relevance": "0.968", "positions_in_text": [22]}, {"tag_name": "KEYWORD", "parsed_value": "hurricane laura emergency", "count": 1, "relevance": "0.968", "positions_in_text": [12]}, {"tag_name": "KEYWORD", "parsed_value": "trump", "count": 1, "relevance": "0.323", "positions_in_text": [0]}, {"tag_name": "KEYWORD", "parsed_value": "ebay", "count": 1, "relevance": "0.323", "positions_in_text": [74]}, {"tag_name": "KEYWORD", "parsed_value": "autographs", "count": 1, "relevance": "0.323", "positions_in_text": [61]}]}, {"text": "Tenants Say They Were Tricked Into RNC Video Appearance: \u2018I Am Not A Trump Supporter\u2019", "external_id": null, "error": false, "extractions": [{"tag_name": "KEYWORD", "parsed_value": "rnc video appearance", "count": 1, "relevance": "0.968", "positions_in_text": [35]}, {"tag_name": "KEYWORD", "parsed_value": "trump supporter\u2019", "count": 1, "relevance": "0.645", "positions_in_text": [69]}, {"tag_name": "KEYWORD", "parsed_value": "tenant", "count": 1, "relevance": "0.323", "positions_in_text": [0]}]}, {"text": "Kanye West campaign in Virginia is accused of deceptive signature gathering", "external_id": null, "error": false, "extractions": [{"tag_name": "KEYWORD", "parsed_value": "deceptive signature gathering", "count": 1, "relevance": "0.968", "positions_in_text": [46]}, {"tag_name": "KEYWORD", "parsed_value": "kanye west campaign", "count": 1, "relevance": "0.968", "positions_in_text": [0]}, {"tag_name": "KEYWORD", "parsed_value": "virginia", "count": 1, "relevance": "0.323", "positions_in_text": [23]}]}, {"text": "Postal service removes Oakland collection boxes; leaders warn of election interference", "external_id": null, "error": false, "extractions": [{"tag_name": "KEYWORD", "parsed_value": "oakland collection box", "count": 1, "relevance": "0.968", "positions_in_text": [23]}, {"tag_name": "KEYWORD", "parsed_value": "postal services", "count": 1, "relevance": "0.645", "positions_in_text": [0]}, {"tag_name": "KEYWORD", "parsed_value": "election interference", "count": 1, "relevance": "0.645", "positions_in_text": [65]}, {"tag_name": "KEYWORD", "parsed_value": "leader", "count": 1, "relevance": "0.323", "positions_in_text": [49]}]}, {"text": "Trump is Allowing Right-Wing Extremists to 'Start a Race War,' Ex-DHS Official Says", "external_id": null, "error": false, "extractions": [{"tag_name": "KEYWORD", "parsed_value": "race war", "count": 1, "relevance": "0.952", "positions_in_text": [52]}, {"tag_name": "KEYWORD", "parsed_value": "dhs official", "count": 1, "relevance": "0.952", "positions_in_text": [66]}, {"tag_name": "KEYWORD", "parsed_value": "wing extremist", "count": 1, "relevance": "0.952", "positions_in_text": [24]}, {"tag_name": "KEYWORD", "parsed_value": "trump", "count": 1, "relevance": "0.476", "positions_in_text": [0]}]}, {"text": "Judge orders Texas to allow online voter registration with driver's license renewal", "external_id": null, "error": false, "extractions": [{"tag_name": "KEYWORD", "parsed_value": "online voters registration", "count": 1, "relevance": "0.968", "positions_in_text": [28]}, {"tag_name": "KEYWORD", "parsed_value": "license renewal", "count": 1, "relevance": "0.645", "positions_in_text": [68]}, {"tag_name": "KEYWORD", "parsed_value": "driver", "count": 1, "relevance": "0.323", "positions_in_text": [59]}, {"tag_name": "KEYWORD", "parsed_value": "judge", "count": 1, "relevance": "0.323", "positions_in_text": [0]}, {"tag_name": "KEYWORD", "parsed_value": "texas", "count": 1, "relevance": "0.323", "positions_in_text": [13]}]}, {"text": "Kenosha Activists: Militias Tolerated, Protesters Arrested", "external_id": null, "error": false, "extractions": [{"tag_name": "KEYWORD", "parsed_value": "kenosha activists", "count": 1, "relevance": "0.952", "positions_in_text": [0]}, {"tag_name": "KEYWORD", "parsed_value": "militia tolerated", "count": 1, "relevance": "0.952", "positions_in_text": [19]}, {"tag_name": "KEYWORD", "parsed_value": "protesters", "count": 1, "relevance": "0.476", "positions_in_text": [39]}]}, {"text": "Activists At The March On Washington Say Jacob Blake\u2019s Shooting Has Reenergized Black Lives Matter Protests. They Wish It Didn\u2019t Have To.", "external_id": null, "error": false, "extractions": [{"tag_name": "KEYWORD", "parsed_value": "say jacob blake", "count": 1, "relevance": "0.968", "positions_in_text": [37]}, {"tag_name": "KEYWORD", "parsed_value": "reenergized black life", "count": 1, "relevance": "0.968", "positions_in_text": [68]}, {"tag_name": "KEYWORD", "parsed_value": "black life matter", "count": 1, "relevance": "0.968", "positions_in_text": [80]}, {"tag_name": "KEYWORD", "parsed_value": "washington say jacob", "count": 1, "relevance": "0.968", "positions_in_text": [26]}, {"tag_name": "KEYWORD", "parsed_value": "life matter protest", "count": 1, "relevance": "0.968", "positions_in_text": [86]}, {"tag_name": "KEYWORD", "parsed_value": "march", "count": 1, "relevance": "0.323", "positions_in_text": [17]}, {"tag_name": "KEYWORD", "parsed_value": "activists", "count": 1, "relevance": "0.323", "positions_in_text": [0]}, {"tag_name": "KEYWORD", "parsed_value": "shooting", "count": 1, "relevance": "0.323", "positions_in_text": [55]}]}, {"text": "Kenosha Police Chief Defends Officers Who Let Alleged Shooter Walk Right by Them", "external_id": null, "error": false, "extractions": [{"tag_name": "KEYWORD", "parsed_value": "kenosha police chief", "count": 1, "relevance": "0.968", "positions_in_text": [0]}, {"tag_name": "KEYWORD", "parsed_value": "police chief defends", "count": 1, "relevance": "0.968", "positions_in_text": [8]}, {"tag_name": "KEYWORD", "parsed_value": "chief defends officer", "count": 1, "relevance": "0.968", "positions_in_text": [15]}, {"tag_name": "KEYWORD", "parsed_value": "alleged shooter", "count": 1, "relevance": "0.645", "positions_in_text": [46]}]}, {"text": "Trump and the GOP want voters to fear 'chaos and anarchy' under Biden, but not the coronavirus that's killing 1,100 Americans a day", "external_id": null, "error": false, "extractions": [{"tag_name": "KEYWORD", "parsed_value": "voters", "count": 1, "relevance": "0.909", "positions_in_text": [23]}, {"tag_name": "KEYWORD", "parsed_value": "trump", "count": 1, "relevance": "0.909", "positions_in_text": [0]}, {"tag_name": "KEYWORD", "parsed_value": "chaos", "count": 1, "relevance": "0.909", "positions_in_text": [39]}, {"tag_name": "KEYWORD", "parsed_value": "anarchy", "count": 1, "relevance": "0.909", "positions_in_text": [49]}, {"tag_name": "KEYWORD", "parsed_value": "biden", "count": 1, "relevance": "0.909", "positions_in_text": [64]}, {"tag_name": "KEYWORD", "parsed_value": "american", "count": 1, "relevance": "0.909", "positions_in_text": [116]}, {"tag_name": "KEYWORD", "parsed_value": "coronavirus", "count": 1, "relevance": "0.909", "positions_in_text": [83]}, {"tag_name": "KEYWORD", "parsed_value": "gop", "count": 1, "relevance": "0.909", "positions_in_text": [14]}, {"tag_name": "KEYWORD", "parsed_value": "day", "count": 1, "relevance": "0.909", "positions_in_text": [128]}]}, {"text": "The Violent Delights of the Trumpian Right | In the end, it was always going to be about blood and soil and gun-toting vigilantes.", "external_id": null, "error": false, "extractions": [{"tag_name": "KEYWORD", "parsed_value": "violent delight", "count": 1, "relevance": "0.952", "positions_in_text": [4]}, {"tag_name": "KEYWORD", "parsed_value": "trumpian rights", "count": 1, "relevance": "0.952", "positions_in_text": [28]}, {"tag_name": "KEYWORD", "parsed_value": "end", "count": 1, "relevance": "0.476", "positions_in_text": [52]}, {"tag_name": "KEYWORD", "parsed_value": "soil", "count": 1, "relevance": "0.476", "positions_in_text": [99]}, {"tag_name": "KEYWORD", "parsed_value": "gun", "count": 1, "relevance": "0.476", "positions_in_text": [108]}, {"tag_name": "KEYWORD", "parsed_value": "blood", "count": 1, "relevance": "0.476", "positions_in_text": [89]}, {"tag_name": "KEYWORD", "parsed_value": "vigilante", "count": 1, "relevance": "0.476", "positions_in_text": [119]}]}, {"text": "Jim Gaffigan slams Trump on Twitter during RNC speech: \"He is a fascist who has no belief in law\"", "external_id": null, "error": false, "extractions": [{"tag_name": "KEYWORD", "parsed_value": "rnc speech", "count": 1, "relevance": "0.952", "positions_in_text": [43]}, {"tag_name": "KEYWORD", "parsed_value": "jim gaffigan", "count": 1, "relevance": "0.952", "positions_in_text": [0]}, {"tag_name": "KEYWORD", "parsed_value": "trump", "count": 1, "relevance": "0.476", "positions_in_text": [19]}, {"tag_name": "KEYWORD", "parsed_value": "fascist", "count": 1, "relevance": "0.476", "positions_in_text": [64]}, {"tag_name": "KEYWORD", "parsed_value": "twitter", "count": 1, "relevance": "0.476", "positions_in_text": [28]}, {"tag_name": "KEYWORD", "parsed_value": "law", "count": 1, "relevance": "0.476", "positions_in_text": [93]}, {"tag_name": "KEYWORD", "parsed_value": "believes", "count": 1, "relevance": "0.476", "positions_in_text": [83]}]}, {"text": "'How dare we not vote?' Black voters organize after DC march", "external_id": null, "error": false, "extractions": [{"tag_name": "KEYWORD", "parsed_value": "black voters", "count": 1, "relevance": "0.952", "positions_in_text": [24]}, {"tag_name": "KEYWORD", "parsed_value": "dc march", "count": 1, "relevance": "0.952", "positions_in_text": [52]}]}, {"text": "Trump administration halts election security briefings for Congress, citing leaks", "external_id": null, "error": false, "extractions": [{"tag_name": "KEYWORD", "parsed_value": "election security briefing", "count": 1, "relevance": "0.968", "positions_in_text": [27]}, {"tag_name": "KEYWORD", "parsed_value": "trump administration", "count": 1, "relevance": "0.645", "positions_in_text": [0]}, {"tag_name": "KEYWORD", "parsed_value": "congress", "count": 1, "relevance": "0.323", "positions_in_text": [59]}, {"tag_name": "KEYWORD", "parsed_value": "leak", "count": 1, "relevance": "0.323", "positions_in_text": [76]}]}, {"text": "Elizabeth Warren calls for investigation into Trump\u2019s politicization of Covid-19", "external_id": null, "error": false, "extractions": [{"tag_name": "KEYWORD", "parsed_value": "politicization of covid-19", "count": 1, "relevance": "0.968", "positions_in_text": [54]}, {"tag_name": "KEYWORD", "parsed_value": "elizabeth warren", "count": 1, "relevance": "0.645", "positions_in_text": [0]}, {"tag_name": "KEYWORD", "parsed_value": "investigation", "count": 1, "relevance": "0.323", "positions_in_text": [27]}, {"tag_name": "KEYWORD", "parsed_value": "trump", "count": 1, "relevance": "0.323", "positions_in_text": [46]}]}, {"text": "Yale psychiatrist: Trump\u2019s convention lies and fear-mongering may \u201cprovoke a lot of violence\u201d", "external_id": null, "error": false, "extractions": [{"tag_name": "KEYWORD", "parsed_value": "lot of violence", "count": 1, "relevance": "0.968", "positions_in_text": [77]}, {"tag_name": "KEYWORD", "parsed_value": "yale psychiatrist", "count": 1, "relevance": "0.645", "positions_in_text": [0]}, {"tag_name": "KEYWORD", "parsed_value": "convention", "count": 1, "relevance": "0.323", "positions_in_text": [27]}, {"tag_name": "KEYWORD", "parsed_value": "trump", "count": 1, "relevance": "0.323", "positions_in_text": [19]}, {"tag_name": "KEYWORD", "parsed_value": "fear", "count": 1, "relevance": "0.323", "positions_in_text": [47]}, {"tag_name": "KEYWORD", "parsed_value": "mongering", "count": 1, "relevance": "0.323", "positions_in_text": [52]}]}, {"text": "Social Security fund would run out of money in 3 years if Trump eliminates payroll tax: SSA analysis", "external_id": null, "error": false, "extractions": [{"tag_name": "KEYWORD", "parsed_value": "social security fund", "count": 1, "relevance": "0.968", "positions_in_text": [0]}, {"tag_name": "KEYWORD", "parsed_value": "payroll tax", "count": 1, "relevance": "0.645", "positions_in_text": [75]}, {"tag_name": "KEYWORD", "parsed_value": "ssa analysis", "count": 1, "relevance": "0.645", "positions_in_text": [88]}, {"tag_name": "KEYWORD", "parsed_value": "trump", "count": 1, "relevance": "0.323", "positions_in_text": [58]}, {"tag_name": "KEYWORD", "parsed_value": "money", "count": 1, "relevance": "0.323", "positions_in_text": [38]}, {"tag_name": "KEYWORD", "parsed_value": "year", "count": 1, "relevance": "0.323", "positions_in_text": [49]}]}, {"text": "Trump Slams Niece After She Reveals New Audio of President\u2019s Sister Swiping at Ivanka, Eric", "external_id": null, "error": false, "extractions": [{"tag_name": "KEYWORD", "parsed_value": "trump slam niece", "count": 1, "relevance": "0.968", "positions_in_text": [0]}, {"tag_name": "KEYWORD", "parsed_value": "audio of president", "count": 1, "relevance": "0.968", "positions_in_text": [40]}, {"tag_name": "KEYWORD", "parsed_value": "new audio", "count": 1, "relevance": "0.645", "positions_in_text": [36]}, {"tag_name": "KEYWORD", "parsed_value": "sister swiping", "count": 1, "relevance": "0.645", "positions_in_text": [61]}, {"tag_name": "KEYWORD", "parsed_value": "ivanka", "count": 1, "relevance": "0.323", "positions_in_text": [79]}, {"tag_name": "KEYWORD", "parsed_value": "eric", "count": 1, "relevance": "0.323", "positions_in_text": [87]}]}, {"text": "US sliding towards autocracy under Trump, former Russian ambassador warns", "external_id": null, "error": false, "extractions": [{"tag_name": "KEYWORD", "parsed_value": "former russian ambassador", "count": 1, "relevance": "0.968", "positions_in_text": [42]}, {"tag_name": "KEYWORD", "parsed_value": "trump", "count": 1, "relevance": "0.323", "positions_in_text": [35]}, {"tag_name": "KEYWORD", "parsed_value": "autocracy", "count": 1, "relevance": "0.323", "positions_in_text": [19]}]}, {"text": "White Supremacists Were 'On A Hunting Spree' In Kenosha, Says Local Lawmaker \u2014 they were \u201cdriving around in pickup trucks, targeting protesters,\u201d said state Rep. David Bowen.", "external_id": null, "error": false, "extractions": [{"tag_name": "KEYWORD", "parsed_value": "rep. david bowen", "count": 1, "relevance": "0.968", "positions_in_text": [157]}, {"tag_name": "KEYWORD", "parsed_value": "state rep. david", "count": 1, "relevance": "0.968", "positions_in_text": [151]}, {"tag_name": "KEYWORD", "parsed_value": "local lawmakers", "count": 1, "relevance": "0.645", "positions_in_text": [62]}, {"tag_name": "KEYWORD", "parsed_value": "white supremacist", "count": 1, "relevance": "0.645", "positions_in_text": [0]}, {"tag_name": "KEYWORD", "parsed_value": "pickup truck", "count": 1, "relevance": "0.645", "positions_in_text": [108]}, {"tag_name": "KEYWORD", "parsed_value": "hunting spree", "count": 1, "relevance": "0.645", "positions_in_text": [30]}, {"tag_name": "KEYWORD", "parsed_value": "protesters", "count": 1, "relevance": "0.323", "positions_in_text": [133]}, {"tag_name": "KEYWORD", "parsed_value": "kenosha", "count": 1, "relevance": "0.323", "positions_in_text": [48]}]}, {"text": "Trump lashes out at 'unstable' niece whose book included devastating psychological profile of him | President complains about series of books by people close to him that portray him as incompetent, paranoid and cruel", "external_id": null, "error": false, "extractions": [{"tag_name": "KEYWORD", "parsed_value": "devastating psychological profile", "count": 1, "relevance": "0.968", "positions_in_text": [57]}, {"tag_name": "KEYWORD", "parsed_value": "series of books", "count": 1, "relevance": "0.968", "positions_in_text": [126]}, {"tag_name": "KEYWORD", "parsed_value": "president", "count": 1, "relevance": "0.323", "positions_in_text": [100]}, {"tag_name": "KEYWORD", "parsed_value": "books", "count": 2, "relevance": "0.323", "positions_in_text": [43, 136]}, {"tag_name": "KEYWORD", "parsed_value": "trump", "count": 1, "relevance": "0.323", "positions_in_text": [0]}, {"tag_name": "KEYWORD", "parsed_value": "people", "count": 1, "relevance": "0.323", "positions_in_text": [145]}, {"tag_name": "KEYWORD", "parsed_value": "niece", "count": 1, "relevance": "0.323", "positions_in_text": [31]}]}, {"text": "Trump's sister brands Ivanka Trump as a 'mini Donald' and Eric as a 'moron' in secret tapes", "external_id": null, "error": false, "extractions": [{"tag_name": "KEYWORD", "parsed_value": "ivanka trump", "count": 1, "relevance": "0.952", "positions_in_text": [22]}, {"tag_name": "KEYWORD", "parsed_value": "secret tape", "count": 1, "relevance": "0.952", "positions_in_text": [79]}, {"tag_name": "KEYWORD", "parsed_value": "mini donald", "count": 1, "relevance": "0.952", "positions_in_text": [41]}, {"tag_name": "KEYWORD", "parsed_value": "sister", "count": 1, "relevance": "0.476", "positions_in_text": [8]}, {"tag_name": "KEYWORD", "parsed_value": "trump", "count": 2, "relevance": "0.476", "positions_in_text": [0, 29]}, {"tag_name": "KEYWORD", "parsed_value": "moron", "count": 1, "relevance": "0.476", "positions_in_text": [69]}, {"tag_name": "KEYWORD", "parsed_value": "eric", "count": 1, "relevance": "0.476", "positions_in_text": [58]}]}, {"text": "Warner calls Intelligence chief's decision to scale down congressional election security briefings 'outrageous'", "external_id": null, "error": false, "extractions": [{"tag_name": "KEYWORD", "parsed_value": "election security briefing", "count": 1, "relevance": "0.968", "positions_in_text": [71]}, {"tag_name": "KEYWORD", "parsed_value": "intelligence chief", "count": 1, "relevance": "0.645", "positions_in_text": [13]}, {"tag_name": "KEYWORD", "parsed_value": "decision", "count": 1, "relevance": "0.323", "positions_in_text": [34]}, {"tag_name": "KEYWORD", "parsed_value": "warner", "count": 1, "relevance": "0.323", "positions_in_text": [0]}]}, {"text": "Oakland Lawmaker Denounces Pence For Linking Officer's Killing To Protests, Omitting Alt-Right 'Boogaloo' Arrest", "external_id": null, "error": false, "extractions": [{"tag_name": "KEYWORD", "parsed_value": "oakland lawmakers denounces", "count": 1, "relevance": "0.968", "positions_in_text": [0]}, {"tag_name": "KEYWORD", "parsed_value": "lawmakers denounces penny", "count": 1, "relevance": "0.968", "positions_in_text": [8]}, {"tag_name": "KEYWORD", "parsed_value": "linking officer", "count": 1, "relevance": "0.645", "positions_in_text": [37]}, {"tag_name": "KEYWORD", "parsed_value": "rights", "count": 1, "relevance": "0.323", "positions_in_text": [89]}, {"tag_name": "KEYWORD", "parsed_value": "killing", "count": 1, "relevance": "0.323", "positions_in_text": [55]}, {"tag_name": "KEYWORD", "parsed_value": "arrest", "count": 1, "relevance": "0.323", "positions_in_text": [106]}, {"tag_name": "KEYWORD", "parsed_value": "protest", "count": 1, "relevance": "0.323", "positions_in_text": [66]}, {"tag_name": "KEYWORD", "parsed_value": "boogaloo", "count": 1, "relevance": "0.323", "positions_in_text": [96]}, {"tag_name": "KEYWORD", "parsed_value": "alt", "count": 1, "relevance": "0.323", "positions_in_text": [85]}]}, {"text": "Exposing Trump's Payroll Tax Deferral as 'Wage Theft,' Treasury Signals Millions of Workers Will Earn Less in 2021 Under Plan | \"Like Donald Trump's other economic executive orders, this will not provide actual relief to workers.\"", "external_id": null, "error": false, "extractions": [{"tag_name": "KEYWORD", "parsed_value": "payroll tax deferral", "count": 1, "relevance": "0.968", "positions_in_text": [17]}, {"tag_name": "KEYWORD", "parsed_value": "economic executive order", "count": 1, "relevance": "0.968", "positions_in_text": [155]}, {"tag_name": "KEYWORD", "parsed_value": "million of workers", "count": 1, "relevance": "0.968", "positions_in_text": [72]}, {"tag_name": "KEYWORD", "parsed_value": "treasury signal million", "count": 1, "relevance": "0.968", "positions_in_text": [55]}, {"tag_name": "KEYWORD", "parsed_value": "actual relief", "count": 1, "relevance": "0.645", "positions_in_text": [204]}, {"tag_name": "KEYWORD", "parsed_value": "donald trump", "count": 1, "relevance": "0.645", "positions_in_text": [134]}, {"tag_name": "KEYWORD", "parsed_value": "wage theft", "count": 1, "relevance": "0.645", "positions_in_text": [42]}, {"tag_name": "KEYWORD", "parsed_value": "trump", "count": 2, "relevance": "0.323", "positions_in_text": [9, 141]}, {"tag_name": "KEYWORD", "parsed_value": "plan", "count": 1, "relevance": "0.323", "positions_in_text": [121]}, {"tag_name": "KEYWORD", "parsed_value": "workers", "count": 2, "relevance": "0.323", "positions_in_text": [84, 221]}]}, {"text": "CNN fact-checked Trump\u2019s RNC speech on air. It took three minutes.", "external_id": null, "error": false, "extractions": [{"tag_name": "KEYWORD", "parsed_value": "checked trump", "count": 1, "relevance": "0.952", "positions_in_text": [9]}, {"tag_name": "KEYWORD", "parsed_value": "rnc speech", "count": 1, "relevance": "0.952", "positions_in_text": [25]}, {"tag_name": "KEYWORD", "parsed_value": "cnn fact", "count": 1, "relevance": "0.952", "positions_in_text": [0]}, {"tag_name": "KEYWORD", "parsed_value": "minutes", "count": 1, "relevance": "0.476", "positions_in_text": [58]}, {"tag_name": "KEYWORD", "parsed_value": "air", "count": 1, "relevance": "0.476", "positions_in_text": [39]}]}, {"text": "Kamala Harris is as eager to destroy Mike Pence as you are to watch her do it \u2014 We'd like to report a murder that hasn't happened yet. It was premeditated.", "external_id": null, "error": false, "extractions": [{"tag_name": "KEYWORD", "parsed_value": "kamala harris", "count": 1, "relevance": "0.952", "positions_in_text": [0]}, {"tag_name": "KEYWORD", "parsed_value": "mike penny", "count": 1, "relevance": "0.952", "positions_in_text": [37]}, {"tag_name": "KEYWORD", "parsed_value": "murder", "count": 1, "relevance": "0.476", "positions_in_text": [102]}]}, {"text": "Biden, aiming at Trump, says he won\u2019t use military as \u2018prop\u2019", "external_id": null, "error": false, "extractions": [{"tag_name": "KEYWORD", "parsed_value": "biden", "count": 1, "relevance": "0.909", "positions_in_text": [0]}, {"tag_name": "KEYWORD", "parsed_value": "military", "count": 1, "relevance": "0.909", "positions_in_text": [42]}, {"tag_name": "KEYWORD", "parsed_value": "prop\u2019", "count": 1, "relevance": "0.909", "positions_in_text": [55]}, {"tag_name": "KEYWORD", "parsed_value": "trump", "count": 1, "relevance": "0.909", "positions_in_text": [17]}]}, {"text": "Kenosha Tells Us More About Where the Right Is Headed Than the R.N.C. Did", "external_id": null, "error": false, "extractions": [{"tag_name": "KEYWORD", "parsed_value": "rights", "count": 1, "relevance": "0.909", "positions_in_text": [38]}, {"tag_name": "KEYWORD", "parsed_value": "r.n.c.", "count": 1, "relevance": "0.909", "positions_in_text": [63]}, {"tag_name": "KEYWORD", "parsed_value": "kenosha", "count": 1, "relevance": "0.909", "positions_in_text": [0]}]}, {"text": "Biden rejects skipping Trump debates, vows to fact-check", "external_id": null, "error": false, "extractions": [{"tag_name": "KEYWORD", "parsed_value": "biden reject", "count": 1, "relevance": "0.952", "positions_in_text": [0]}, {"tag_name": "KEYWORD", "parsed_value": "trump debate", "count": 1, "relevance": "0.952", "positions_in_text": [23]}, {"tag_name": "KEYWORD", "parsed_value": "check", "count": 1, "relevance": "0.476", "positions_in_text": [51]}, {"tag_name": "KEYWORD", "parsed_value": "fact", "count": 1, "relevance": "0.476", "positions_in_text": [46]}]}, {"text": "Director of National Intelligence Cancels Election Security Briefings, Democrats Say", "external_id": null, "error": false, "extractions": [{"tag_name": "KEYWORD", "parsed_value": "intelligence cancel election", "count": 1, "relevance": "0.968", "positions_in_text": [21]}, {"tag_name": "KEYWORD", "parsed_value": "director of national", "count": 1, "relevance": "0.968", "positions_in_text": [0]}, {"tag_name": "KEYWORD", "parsed_value": "national intelligence cancel", "count": 1, "relevance": "0.968", "positions_in_text": [12]}, {"tag_name": "KEYWORD", "parsed_value": "election security briefing", "count": 1, "relevance": "0.968", "positions_in_text": [42]}, {"tag_name": "KEYWORD", "parsed_value": "cancel election security", "count": 1, "relevance": "0.968", "positions_in_text": [34]}, {"tag_name": "KEYWORD", "parsed_value": "democrats", "count": 1, "relevance": "0.323", "positions_in_text": [71]}]}, {"text": "Those \u2018lifelong Jewish Democrats\u2019 voting for Trump? Turns out half of them usually vote Republican", "external_id": null, "error": false, "extractions": [{"tag_name": "KEYWORD", "parsed_value": "jewish democrats\u2019 voting", "count": 1, "relevance": "0.968", "positions_in_text": [16]}, {"tag_name": "KEYWORD", "parsed_value": "lifelong jewish democrats\u2019", "count": 1, "relevance": "0.968", "positions_in_text": [7]}, {"tag_name": "KEYWORD", "parsed_value": "trump", "count": 1, "relevance": "0.323", "positions_in_text": [45]}, {"tag_name": "KEYWORD", "parsed_value": "half", "count": 1, "relevance": "0.323", "positions_in_text": [62]}]}, {"text": "FBI to Senate: We\u2019re Investigating 1,000 White Supremacists. Senate to FBI: That\u2019s All?", "external_id": null, "error": false, "extractions": [{"tag_name": "KEYWORD", "parsed_value": "senate", "count": 2, "relevance": "0.952", "positions_in_text": [7, 61]}, {"tag_name": "KEYWORD", "parsed_value": "fbi", "count": 2, "relevance": "0.952", "positions_in_text": [0, 71]}, {"tag_name": "KEYWORD", "parsed_value": "white supremacist", "count": 1, "relevance": "0.952", "positions_in_text": [41]}]}, {"text": "Chadwick Boseman\u2019s last tweet was in support of Kamala Harris", "external_id": null, "error": false, "extractions": [{"tag_name": "KEYWORD", "parsed_value": "support of kamala", "count": 1, "relevance": "0.968", "positions_in_text": [37]}, {"tag_name": "KEYWORD", "parsed_value": "kamala harris", "count": 1, "relevance": "0.645", "positions_in_text": [48]}, {"tag_name": "KEYWORD", "parsed_value": "last tweet", "count": 1, "relevance": "0.645", "positions_in_text": [19]}, {"tag_name": "KEYWORD", "parsed_value": "chadwick boseman", "count": 1, "relevance": "0.645", "positions_in_text": [0]}]}, {"text": "Pelosi, Schiff pan director of national intelligence for canceling election security briefings", "external_id": null, "error": false, "extractions": [{"tag_name": "KEYWORD", "parsed_value": "schiff pan director", "count": 1, "relevance": "0.968", "positions_in_text": [8]}, {"tag_name": "KEYWORD", "parsed_value": "election security briefing", "count": 1, "relevance": "0.968", "positions_in_text": [67]}, {"tag_name": "KEYWORD", "parsed_value": "national intelligence", "count": 1, "relevance": "0.645", "positions_in_text": [31]}, {"tag_name": "KEYWORD", "parsed_value": "pelosi", "count": 1, "relevance": "0.323", "positions_in_text": [0]}]}, {"text": "Obama counseled NBA players on forming a social justice committee", "external_id": null, "error": false, "extractions": [{"tag_name": "KEYWORD", "parsed_value": "social justice committee", "count": 1, "relevance": "0.968", "positions_in_text": [41]}, {"tag_name": "KEYWORD", "parsed_value": "nba player", "count": 1, "relevance": "0.645", "positions_in_text": [16]}, {"tag_name": "KEYWORD", "parsed_value": "obama", "count": 1, "relevance": "0.323", "positions_in_text": [0]}]}, {"text": "Father of Navy SEAL who died in raid in early days of Trump presidency issues a warning in ad", "external_id": null, "error": false, "extractions": [{"tag_name": "KEYWORD", "parsed_value": "father of navy", "count": 1, "relevance": "0.968", "positions_in_text": [0]}, {"tag_name": "KEYWORD", "parsed_value": "trump presidency issues", "count": 1, "relevance": "0.968", "positions_in_text": [54]}, {"tag_name": "KEYWORD", "parsed_value": "early day", "count": 1, "relevance": "0.645", "positions_in_text": [40]}, {"tag_name": "KEYWORD", "parsed_value": "navy seal", "count": 1, "relevance": "0.645", "positions_in_text": [10]}, {"tag_name": "KEYWORD", "parsed_value": "raid", "count": 1, "relevance": "0.323", "positions_in_text": [32]}, {"tag_name": "KEYWORD", "parsed_value": "ad", "count": 1, "relevance": "0.323", "positions_in_text": [91]}, {"tag_name": "KEYWORD", "parsed_value": "warning", "count": 1, "relevance": "0.323", "positions_in_text": [80]}]}, {"text": "A dictator on downers: Slow-motion mass hysteria at the Republican convention - Donald Trump's speech was depressing and soulless, even for him. He can taste doom coming, and he doesn't like it", "external_id": null, "error": false, "extractions": [{"tag_name": "KEYWORD", "parsed_value": "motion mass hysteria", "count": 1, "relevance": "0.968", "positions_in_text": [28]}, {"tag_name": "KEYWORD", "parsed_value": "donald trump", "count": 1, "relevance": "0.645", "positions_in_text": [80]}, {"tag_name": "KEYWORD", "parsed_value": "republican convention", "count": 1, "relevance": "0.645", "positions_in_text": [56]}, {"tag_name": "KEYWORD", "parsed_value": "dictator", "count": 1, "relevance": "0.323", "positions_in_text": [2]}, {"tag_name": "KEYWORD", "parsed_value": "speech", "count": 1, "relevance": "0.323", "positions_in_text": [95]}, {"tag_name": "KEYWORD", "parsed_value": "doom", "count": 1, "relevance": "0.323", "positions_in_text": [158]}, {"tag_name": "KEYWORD", "parsed_value": "downer", "count": 1, "relevance": "0.323", "positions_in_text": [14]}]}, {"text": "Republican candidate for US House Seat refuses to debate opponent", "external_id": null, "error": false, "extractions": [{"tag_name": "KEYWORD", "parsed_value": "us house seat", "count": 1, "relevance": "0.968", "positions_in_text": [25]}, {"tag_name": "KEYWORD", "parsed_value": "republican candidate", "count": 1, "relevance": "0.645", "positions_in_text": [0]}, {"tag_name": "KEYWORD", "parsed_value": "opponent", "count": 1, "relevance": "0.323", "positions_in_text": [57]}]}, {"text": "If Republicans really cared about hurricane victims, they'd stop denying climate change \u2014 Thoughts and prayers are not enough and never have been. But the GOP is determined to deny climate change regardless of the consequences to our nation.", "external_id": null, "error": false, "extractions": [{"tag_name": "KEYWORD", "parsed_value": "climate change", "count": 2, "relevance": "0.976", "positions_in_text": [73, 181]}, {"tag_name": "KEYWORD", "parsed_value": "hurricane victims", "count": 1, "relevance": "0.488", "positions_in_text": [34]}, {"tag_name": "KEYWORD", "parsed_value": "nation", "count": 1, "relevance": "0.244", "positions_in_text": [234]}, {"tag_name": "KEYWORD", "parsed_value": "thought", "count": 1, "relevance": "0.244", "positions_in_text": [90]}, {"tag_name": "KEYWORD", "parsed_value": "prayer", "count": 1, "relevance": "0.244", "positions_in_text": [103]}, {"tag_name": "KEYWORD", "parsed_value": "consequences", "count": 1, "relevance": "0.244", "positions_in_text": [214]}, {"tag_name": "KEYWORD", "parsed_value": "republican", "count": 1, "relevance": "0.244", "positions_in_text": [3]}, {"tag_name": "KEYWORD", "parsed_value": "gop", "count": 1, "relevance": "0.244", "positions_in_text": [155]}]}, {"text": "Do Republicans Know \u201cHallelujah\u201d Is About Sex?", "external_id": null, "error": false, "extractions": [{"tag_name": "KEYWORD", "parsed_value": "republican", "count": 1, "relevance": "0.909", "positions_in_text": [3]}, {"tag_name": "KEYWORD", "parsed_value": "hallelujah", "count": 1, "relevance": "0.909", "positions_in_text": [21]}, {"tag_name": "KEYWORD", "parsed_value": "sex", "count": 1, "relevance": "0.909", "positions_in_text": [42]}]}, {"text": "Democrats Look to Hatch Act to Try to Stop Trump Administration from Politicizing Government", "external_id": null, "error": false, "extractions": [{"tag_name": "KEYWORD", "parsed_value": "politicizing government", "count": 1, "relevance": "0.952", "positions_in_text": [69]}, {"tag_name": "KEYWORD", "parsed_value": "hatch act", "count": 1, "relevance": "0.952", "positions_in_text": [18]}, {"tag_name": "KEYWORD", "parsed_value": "trump administration", "count": 1, "relevance": "0.952", "positions_in_text": [43]}, {"tag_name": "KEYWORD", "parsed_value": "democrats", "count": 1, "relevance": "0.476", "positions_in_text": [0]}]}, {"text": "Trump\u2019s \u2018Weird Shit\u2019 Is Rotting Our Democracy", "external_id": null, "error": false, "extractions": [{"tag_name": "KEYWORD", "parsed_value": "weird shit\u2019", "count": 1, "relevance": "0.952", "positions_in_text": [9]}, {"tag_name": "KEYWORD", "parsed_value": "trump", "count": 1, "relevance": "0.476", "positions_in_text": [0]}, {"tag_name": "KEYWORD", "parsed_value": "democracy", "count": 1, "relevance": "0.476", "positions_in_text": [36]}]}, {"text": "House will vote on removing cannabis from controlled substances list", "external_id": null, "error": false, "extractions": [{"tag_name": "KEYWORD", "parsed_value": "controlled substance list", "count": 1, "relevance": "0.968", "positions_in_text": [42]}, {"tag_name": "KEYWORD", "parsed_value": "cannabis", "count": 1, "relevance": "0.323", "positions_in_text": [28]}, {"tag_name": "KEYWORD", "parsed_value": "house", "count": 1, "relevance": "0.323", "positions_in_text": [0]}]}, {"text": "How to commit mail-in voting fraud (It's nearly impossible) - Election officials and the FBI say it's almost impossible to pull off fraud via mail-in ballots. Spreading disinformation about voting-by-mail is much easier.", "external_id": null, "error": false, "extractions": [{"tag_name": "KEYWORD", "parsed_value": "mail", "count": 3, "relevance": "0.968", "positions_in_text": [14, 142, 200]}, {"tag_name": "KEYWORD", "parsed_value": "voting fraud", "count": 1, "relevance": "0.645", "positions_in_text": [22]}, {"tag_name": "KEYWORD", "parsed_value": "election official", "count": 1, "relevance": "0.645", "positions_in_text": [62]}, {"tag_name": "KEYWORD", "parsed_value": "fraud", "count": 2, "relevance": "0.323", "positions_in_text": [29, 132]}, {"tag_name": "KEYWORD", "parsed_value": "disinformation", "count": 1, "relevance": "0.323", "positions_in_text": [169]}, {"tag_name": "KEYWORD", "parsed_value": "fbi", "count": 1, "relevance": "0.323", "positions_in_text": [89]}, {"tag_name": "KEYWORD", "parsed_value": "voting", "count": 2, "relevance": "0.323", "positions_in_text": [22, 190]}, {"tag_name": "KEYWORD", "parsed_value": "ballot", "count": 1, "relevance": "0.323", "positions_in_text": [150]}]}, {"text": "Biden, Trump tussle over whose America is dangerous - \"Ask yourself: Do you feel safe in Trump\u2019s America?\" Biden says in a new video.", "external_id": null, "error": false, "extractions": [{"tag_name": "KEYWORD", "parsed_value": "biden", "count": 2, "relevance": "0.952", "positions_in_text": [0, 107]}, {"tag_name": "KEYWORD", "parsed_value": "new video", "count": 1, "relevance": "0.952", "positions_in_text": [123]}, {"tag_name": "KEYWORD", "parsed_value": "america", "count": 2, "relevance": "0.952", "positions_in_text": [31, 97]}, {"tag_name": "KEYWORD", "parsed_value": "trump tussle", "count": 1, "relevance": "0.952", "positions_in_text": [7]}, {"tag_name": "KEYWORD", "parsed_value": "trump", "count": 2, "relevance": "0.476", "positions_in_text": [7, 89]}]}, {"text": "Hogan Administration Official Fired After Posts Show Support for Wisconsin Shooting Suspect", "external_id": null, "error": false, "extractions": [{"tag_name": "KEYWORD", "parsed_value": "wisconsin shooting suspect", "count": 1, "relevance": "0.968", "positions_in_text": [65]}, {"tag_name": "KEYWORD", "parsed_value": "hogan administration official", "count": 1, "relevance": "0.968", "positions_in_text": [0]}, {"tag_name": "KEYWORD", "parsed_value": "post show support", "count": 1, "relevance": "0.968", "positions_in_text": [42]}]}, {"text": "White fear is on the November ballot \u2014 With lies about \u2018violent mobs\u2019 and anarchy, Trump keeps inching this nation toward a civil war.", "external_id": null, "error": false, "extractions": [{"tag_name": "KEYWORD", "parsed_value": "civil war", "count": 1, "relevance": "0.952", "positions_in_text": [124]}, {"tag_name": "KEYWORD", "parsed_value": "white fear", "count": 1, "relevance": "0.952", "positions_in_text": [0]}, {"tag_name": "KEYWORD", "parsed_value": "violent mobs\u2019", "count": 1, "relevance": "0.952", "positions_in_text": [56]}, {"tag_name": "KEYWORD", "parsed_value": "november ballot", "count": 1, "relevance": "0.952", "positions_in_text": [21]}, {"tag_name": "KEYWORD", "parsed_value": "lies", "count": 1, "relevance": "0.476", "positions_in_text": [44]}, {"tag_name": "KEYWORD", "parsed_value": "trump", "count": 1, "relevance": "0.476", "positions_in_text": [83]}, {"tag_name": "KEYWORD", "parsed_value": "anarchy", "count": 1, "relevance": "0.476", "positions_in_text": [74]}, {"tag_name": "KEYWORD", "parsed_value": "nation", "count": 1, "relevance": "0.476", "positions_in_text": [108]}]}, {"text": "IRS tells companies to not take out Social Security taxes from checks following presidential order", "external_id": null, "error": false, "extractions": [{"tag_name": "KEYWORD", "parsed_value": "social security tax", "count": 1, "relevance": "0.968", "positions_in_text": [36]}, {"tag_name": "KEYWORD", "parsed_value": "presidential order", "count": 1, "relevance": "0.645", "positions_in_text": [80]}, {"tag_name": "KEYWORD", "parsed_value": "check", "count": 1, "relevance": "0.323", "positions_in_text": [63]}, {"tag_name": "KEYWORD", "parsed_value": "company", "count": 1, "relevance": "0.323", "positions_in_text": [10]}, {"tag_name": "KEYWORD", "parsed_value": "irs", "count": 1, "relevance": "0.323", "positions_in_text": [0]}]}, {"text": "Trump administration ends election security briefings", "external_id": null, "error": false, "extractions": [{"tag_name": "KEYWORD", "parsed_value": "election security briefing", "count": 1, "relevance": "0.968", "positions_in_text": [26]}, {"tag_name": "KEYWORD", "parsed_value": "trump administration", "count": 1, "relevance": "0.645", "positions_in_text": [0]}]}, {"text": "American Oversight sues for records of complaints about Barr's conduct", "external_id": null, "error": false, "extractions": [{"tag_name": "KEYWORD", "parsed_value": "record of complaint", "count": 1, "relevance": "0.968", "positions_in_text": [28]}, {"tag_name": "KEYWORD", "parsed_value": "american oversight", "count": 1, "relevance": "0.645", "positions_in_text": [0]}, {"tag_name": "KEYWORD", "parsed_value": "barr", "count": 1, "relevance": "0.323", "positions_in_text": [56]}, {"tag_name": "KEYWORD", "parsed_value": "conduct", "count": 1, "relevance": "0.323", "positions_in_text": [63]}]}, {"text": "\u2018Enough Is Enough\u2019: New Racial Justice Leaders Rise in Kenosha", "external_id": null, "error": false, "extractions": [{"tag_name": "KEYWORD", "parsed_value": "racial justice leader", "count": 1, "relevance": "0.968", "positions_in_text": [24]}, {"tag_name": "KEYWORD", "parsed_value": "enough", "count": 2, "relevance": "0.323", "positions_in_text": [1, 11]}, {"tag_name": "KEYWORD", "parsed_value": "kenosha", "count": 1, "relevance": "0.323", "positions_in_text": [55]}, {"tag_name": "KEYWORD", "parsed_value": "new", "count": 1, "relevance": "0.323", "positions_in_text": [20]}]}, {"text": "The Lawmakers Fighting to Make Hair Discrimination Illegal\u2014For decades, schools and workplaces have told Black employees and students that the hair that grows out of our heads is \u201cunprofessional,\u201d \u201cunacceptable\u201d and \u201cunruly.\u201d These legislators are doing everything in their power to put a stop to it.", "external_id": null, "error": false, "extractions": [{"tag_name": "KEYWORD", "parsed_value": "told black employees", "count": 1, "relevance": "0.968", "positions_in_text": [100]}, {"tag_name": "KEYWORD", "parsed_value": "hair discrimination", "count": 1, "relevance": "0.645", "positions_in_text": [31]}, {"tag_name": "KEYWORD", "parsed_value": "school", "count": 1, "relevance": "0.323", "positions_in_text": [72]}, {"tag_name": "KEYWORD", "parsed_value": "power", "count": 1, "relevance": "0.323", "positions_in_text": [274]}, {"tag_name": "KEYWORD", "parsed_value": "lawmakers", "count": 1, "relevance": "0.323", "positions_in_text": [4]}, {"tag_name": "KEYWORD", "parsed_value": "decade", "count": 1, "relevance": "0.323", "positions_in_text": [63]}, {"tag_name": "KEYWORD", "parsed_value": "stop", "count": 1, "relevance": "0.323", "positions_in_text": [289]}, {"tag_name": "KEYWORD", "parsed_value": "head", "count": 1, "relevance": "0.323", "positions_in_text": [170]}, {"tag_name": "KEYWORD", "parsed_value": "hair", "count": 2, "relevance": "0.323", "positions_in_text": [31, 143]}, {"tag_name": "KEYWORD", "parsed_value": "everything", "count": 1, "relevance": "0.323", "positions_in_text": [254]}]}, {"text": "College Republicans Raise Money for Alleged Murderer Kyle Rittenhouse", "external_id": null, "error": false, "extractions": [{"tag_name": "KEYWORD", "parsed_value": "alleged murderer kyle", "count": 1, "relevance": "0.968", "positions_in_text": [36]}, {"tag_name": "KEYWORD", "parsed_value": "murderer kyle rittenhouse", "count": 1, "relevance": "0.968", "positions_in_text": [44]}, {"tag_name": "KEYWORD", "parsed_value": "college republican", "count": 1, "relevance": "0.645", "positions_in_text": [0]}, {"tag_name": "KEYWORD", "parsed_value": "money", "count": 1, "relevance": "0.323", "positions_in_text": [26]}]}, {"text": "Social Security Fund Would Be Depleted in 3 Years If Trump Kills the Payroll Tax", "external_id": null, "error": false, "extractions": [{"tag_name": "KEYWORD", "parsed_value": "social security fund", "count": 1, "relevance": "0.968", "positions_in_text": [0]}, {"tag_name": "KEYWORD", "parsed_value": "trump kill", "count": 1, "relevance": "0.645", "positions_in_text": [53]}, {"tag_name": "KEYWORD", "parsed_value": "payroll tax", "count": 1, "relevance": "0.645", "positions_in_text": [69]}, {"tag_name": "KEYWORD", "parsed_value": "year", "count": 1, "relevance": "0.323", "positions_in_text": [44]}]}, {"text": "How William Barr is Weaponizing the Justice Department to Help Trump Win: Former DOJ Officials Spoke About the Attorney General\u2019s Efforts to Undermine Voting and His Potential to Unleash an \u201cOctober Surprise.\u201d", "external_id": null, "error": false, "extractions": [{"tag_name": "KEYWORD", "parsed_value": "former doj official", "count": 1, "relevance": "0.968", "positions_in_text": [74]}, {"tag_name": "KEYWORD", "parsed_value": "trump win", "count": 1, "relevance": "0.645", "positions_in_text": [63]}, {"tag_name": "KEYWORD", "parsed_value": "undermine voting", "count": 1, "relevance": "0.645", "positions_in_text": [141]}, {"tag_name": "KEYWORD", "parsed_value": "attorney general", "count": 1, "relevance": "0.645", "positions_in_text": [111]}, {"tag_name": "KEYWORD", "parsed_value": "justice department", "count": 1, "relevance": "0.645", "positions_in_text": [36]}, {"tag_name": "KEYWORD", "parsed_value": "william barr", "count": 1, "relevance": "0.645", "positions_in_text": [4]}, {"tag_name": "KEYWORD", "parsed_value": "october surprise", "count": 1, "relevance": "0.645", "positions_in_text": [191]}, {"tag_name": "KEYWORD", "parsed_value": "effort", "count": 1, "relevance": "0.323", "positions_in_text": [130]}, {"tag_name": "KEYWORD", "parsed_value": "weaponizing", "count": 1, "relevance": "0.323", "positions_in_text": [20]}, {"tag_name": "KEYWORD", "parsed_value": "potential", "count": 1, "relevance": "0.323", "positions_in_text": [166]}]}, {"text": "As Trump appointees flout the Hatch Act, civil servants who get caught get punished", "external_id": null, "error": false, "extractions": [{"tag_name": "KEYWORD", "parsed_value": "hatch act", "count": 1, "relevance": "0.952", "positions_in_text": [30]}, {"tag_name": "KEYWORD", "parsed_value": "civil servant", "count": 1, "relevance": "0.952", "positions_in_text": [41]}, {"tag_name": "KEYWORD", "parsed_value": "trump appointee", "count": 1, "relevance": "0.952", "positions_in_text": [3]}]}, {"text": "No More In-Person Election Briefings for Congress, Intelligence Chief Says", "external_id": null, "error": false, "extractions": [{"tag_name": "KEYWORD", "parsed_value": "person election briefing", "count": 1, "relevance": "0.968", "positions_in_text": [11]}, {"tag_name": "KEYWORD", "parsed_value": "intelligence chief", "count": 1, "relevance": "0.645", "positions_in_text": [51]}, {"tag_name": "KEYWORD", "parsed_value": "congress", "count": 1, "relevance": "0.323", "positions_in_text": [41]}]}, {"text": "GOP candidate posts meme praising Kyle Rittenhouse", "external_id": null, "error": false, "extractions": [{"tag_name": "KEYWORD", "parsed_value": "gop candidate post", "count": 1, "relevance": "0.968", "positions_in_text": [0]}, {"tag_name": "KEYWORD", "parsed_value": "candidate post meme", "count": 1, "relevance": "0.968", "positions_in_text": [4]}, {"tag_name": "KEYWORD", "parsed_value": "kyle rittenhouse", "count": 1, "relevance": "0.645", "positions_in_text": [34]}]}, {"text": "Michael Moore warns of 2016 repeat: Enthusiasm for Trump 'off the charts'", "external_id": null, "error": false, "extractions": [{"tag_name": "KEYWORD", "parsed_value": "michael moore", "count": 1, "relevance": "0.952", "positions_in_text": [0]}, {"tag_name": "KEYWORD", "parsed_value": "repeat", "count": 1, "relevance": "0.476", "positions_in_text": [28]}, {"tag_name": "KEYWORD", "parsed_value": "enthusiasm", "count": 1, "relevance": "0.476", "positions_in_text": [36]}, {"tag_name": "KEYWORD", "parsed_value": "chart", "count": 1, "relevance": "0.476", "positions_in_text": [66]}, {"tag_name": "KEYWORD", "parsed_value": "trump", "count": 1, "relevance": "0.476", "positions_in_text": [51]}]}, {"text": "Democrats Must Demolish Trump\u2019s Delusional Law-Breaking Dystopia", "external_id": null, "error": false, "extractions": [{"tag_name": "KEYWORD", "parsed_value": "delusional law", "count": 1, "relevance": "0.952", "positions_in_text": [32]}, {"tag_name": "KEYWORD", "parsed_value": "demolish trump", "count": 1, "relevance": "0.952", "positions_in_text": [15]}, {"tag_name": "KEYWORD", "parsed_value": "dystopia", "count": 1, "relevance": "0.476", "positions_in_text": [56]}, {"tag_name": "KEYWORD", "parsed_value": "democrats", "count": 1, "relevance": "0.476", "positions_in_text": [0]}]}, {"text": "Biden, aiming at Trump, says he won't use military as 'prop'", "external_id": null, "error": false, "extractions": [{"tag_name": "KEYWORD", "parsed_value": "biden", "count": 1, "relevance": "0.909", "positions_in_text": [0]}, {"tag_name": "KEYWORD", "parsed_value": "military", "count": 1, "relevance": "0.909", "positions_in_text": [42]}, {"tag_name": "KEYWORD", "parsed_value": "trump", "count": 1, "relevance": "0.909", "positions_in_text": [17]}, {"tag_name": "KEYWORD", "parsed_value": "prop", "count": 1, "relevance": "0.909", "positions_in_text": [55]}]}, {"text": "Florida Department of Health claims number of COVID-19 cases in schools is confidential", "external_id": null, "error": false, "extractions": [{"tag_name": "KEYWORD", "parsed_value": "department of health", "count": 1, "relevance": "0.968", "positions_in_text": [8]}, {"tag_name": "KEYWORD", "parsed_value": "number of covid-19", "count": 1, "relevance": "0.968", "positions_in_text": [36]}, {"tag_name": "KEYWORD", "parsed_value": "covid-19 case", "count": 1, "relevance": "0.645", "positions_in_text": [46]}, {"tag_name": "KEYWORD", "parsed_value": "florida department", "count": 1, "relevance": "0.645", "positions_in_text": [0]}, {"tag_name": "KEYWORD", "parsed_value": "school", "count": 1, "relevance": "0.323", "positions_in_text": [64]}]}, {"text": "Facebook banned violent right-wing militia groups. We still found plenty of them on its platform.", "external_id": null, "error": false, "extractions": [{"tag_name": "KEYWORD", "parsed_value": "wing militia group", "count": 1, "relevance": "0.968", "positions_in_text": [30]}, {"tag_name": "KEYWORD", "parsed_value": "platform", "count": 1, "relevance": "0.323", "positions_in_text": [88]}, {"tag_name": "KEYWORD", "parsed_value": "facebook", "count": 1, "relevance": "0.323", "positions_in_text": [0]}]}, {"text": "Biden Trolls Trump, Snags 'Keep America Great' Domain | The Trump campaign failed to register the slogan as a domain name", "external_id": null, "error": false, "extractions": [{"tag_name": "KEYWORD", "parsed_value": "biden troll trump", "count": 1, "relevance": "0.968", "positions_in_text": [0]}, {"tag_name": "KEYWORD", "parsed_value": "trump campaign", "count": 1, "relevance": "0.645", "positions_in_text": [60]}, {"tag_name": "KEYWORD", "parsed_value": "america great", "count": 1, "relevance": "0.645", "positions_in_text": [32]}, {"tag_name": "KEYWORD", "parsed_value": "domain name", "count": 1, "relevance": "0.645", "positions_in_text": [110]}, {"tag_name": "KEYWORD", "parsed_value": "slogan", "count": 1, "relevance": "0.323", "positions_in_text": [98]}, {"tag_name": "KEYWORD", "parsed_value": "domain", "count": 2, "relevance": "0.323", "positions_in_text": [47, 110]}, {"tag_name": "KEYWORD", "parsed_value": "snag", "count": 1, "relevance": "0.323", "positions_in_text": [20]}]}, {"text": "Leonard Cohen Estate Considering Legal Action After RNC Plays \u201cHalleujah\u201d", "external_id": null, "error": false, "extractions": [{"tag_name": "KEYWORD", "parsed_value": "estate considering legal", "count": 1, "relevance": "0.968", "positions_in_text": [14]}, {"tag_name": "KEYWORD", "parsed_value": "considering legal action", "count": 1, "relevance": "0.968", "positions_in_text": [21]}, {"tag_name": "KEYWORD", "parsed_value": "cohen estate considering", "count": 1, "relevance": "0.968", "positions_in_text": [8]}, {"tag_name": "KEYWORD", "parsed_value": "leonard cohen estate", "count": 1, "relevance": "0.968", "positions_in_text": [0]}, {"tag_name": "KEYWORD", "parsed_value": "rnc play", "count": 1, "relevance": "0.645", "positions_in_text": [52]}, {"tag_name": "KEYWORD", "parsed_value": "halleujah", "count": 1, "relevance": "0.323", "positions_in_text": [63]}]}, {"text": "Pelosi Demands Nearly $1 Trillion More For Coronavirus Relief Package", "external_id": null, "error": false, "extractions": [{"tag_name": "KEYWORD", "parsed_value": "coronavirus relief package", "count": 1, "relevance": "0.968", "positions_in_text": [43]}, {"tag_name": "KEYWORD", "parsed_value": "pelosi", "count": 1, "relevance": "0.323", "positions_in_text": [0]}]}, {"text": "Mary Trump Condemns RNC, Says Trump Will \u2018Use Anybody For His Own Purposes\u2019", "external_id": null, "error": false, "extractions": [{"tag_name": "KEYWORD", "parsed_value": "mary trump condemns", "count": 1, "relevance": "0.968", "positions_in_text": [0]}, {"tag_name": "KEYWORD", "parsed_value": "trump condemns rnc", "count": 1, "relevance": "0.968", "positions_in_text": [5]}, {"tag_name": "KEYWORD", "parsed_value": "use anybody", "count": 1, "relevance": "0.645", "positions_in_text": [42]}, {"tag_name": "KEYWORD", "parsed_value": "trump", "count": 2, "relevance": "0.323", "positions_in_text": [5, 30]}, {"tag_name": "KEYWORD", "parsed_value": "purposes\u2019", "count": 1, "relevance": "0.323", "positions_in_text": [66]}]}, {"text": "Highlighting Trump's 'Promises Broken,' Sanders to Give Saturday Address on Biden's Plan for the Economy and Working Families", "external_id": null, "error": false, "extractions": [{"tag_name": "KEYWORD", "parsed_value": "promise broken", "count": 1, "relevance": "0.952", "positions_in_text": [22]}, {"tag_name": "KEYWORD", "parsed_value": "highlighting trump", "count": 1, "relevance": "0.952", "positions_in_text": [0]}, {"tag_name": "KEYWORD", "parsed_value": "working family", "count": 1, "relevance": "0.952", "positions_in_text": [109]}, {"tag_name": "KEYWORD", "parsed_value": "saturday address", "count": 1, "relevance": "0.952", "positions_in_text": [56]}, {"tag_name": "KEYWORD", "parsed_value": "sanders", "count": 1, "relevance": "0.476", "positions_in_text": [40]}, {"tag_name": "KEYWORD", "parsed_value": "biden", "count": 1, "relevance": "0.476", "positions_in_text": [76]}, {"tag_name": "KEYWORD", "parsed_value": "plan", "count": 1, "relevance": "0.476", "positions_in_text": [84]}, {"tag_name": "KEYWORD", "parsed_value": "economy", "count": 1, "relevance": "0.476", "positions_in_text": [97]}]}]